emfit/__init__.py
emfit/api.py
emfitapi_python-0.2.3.dist-info/METADATA
emfitapi_python-0.2.3.dist-info/WHEEL
emfitapi_python-0.2.3.dist-info/licenses/LICENSE
emfitapi_python-0.2.3.dist-info/RECORD
