Metadata-Version: 2.4
Name: emfitapi-python
Version: 0.2.3
Summary: Python wrapper for the Emfit QS API
Project-URL: Homepage, https://github.com/harper/emfitapi-python
Project-URL: Repository, https://github.com/harper/emfitapi-python
Project-URL: Issues, https://github.com/harper/emfitapi-python/issues
Author-email: Harper <harper@nata2.org>
License-Expression: MIT
License-File: LICENSE
Classifier: Development Status :: 3 - Alpha
Classifier: Intended Audience :: Developers
Classifier: License :: OSI Approved :: MIT License
Classifier: Operating System :: OS Independent
Classifier: Programming Language :: Python :: 3
Classifier: Programming Language :: Python :: 3.11
Classifier: Programming Language :: Python :: 3.12
Classifier: Programming Language :: Python :: 3.13
Classifier: Topic :: Home Automation
Classifier: Topic :: Scientific/Engineering :: Medical Science Apps.
Classifier: Topic :: Software Development :: Libraries :: Python Modules
Requires-Python: >=3.11
Requires-Dist: python-dotenv>=1.0.1
Requires-Dist: requests>=2.32.3
